[
    {
        "id" : 1, 
        "nombre" : "Trixy", 
        "apellido" : "Powell", 
        "email" : "tpowell0@google.com.au", 
        "genero" : "F", 
        "edad" : 45
    }, 
    {
        "id" : 2, 
        "nombre" : "Madonna", 
        "apellido" : "Champley", 
        "email" : "mchampley1@sbwire.com", 
        "genero" : "F", 
        "edad" : 64
    }, 
    {
        "id" : 3, 
        "nombre" : "Harcourt", 
        "apellido" : "Warham", 
        "email" : "hwarham2@nifty.com", 
        "genero" : "M", 
        "edad" : 62
    }, 
    {
        "id" : 4, 
        "nombre" : "Kinsley", 
        "apellido" : "Keeffe", 
        "email" : "kkeeffe3@deliciousdays.com", 
        "genero" : "M", 
        "edad" : 25
    }, 
    {
        "id" : 5, 
        "nombre" : "Kamillah", 
        "apellido" : "Leggis", 
        "email" : "kleggis4@ox.ac.uk", 
        "genero" : "F", 
        "edad" : 26
    }, 
    {
        "id" : 6, 
        "nombre" : "Carmon", 
        "apellido" : "Emeny", 
        "email" : "cemeny5@imageshack.us", 
        "genero" : "F", 
        "edad" : 59
    }, 
    {
        "id" : 7, 
        "nombre" : "Elsey", 
        "apellido" : "Tween", 
        "email" : "etween6@icio.us", 
        "genero" : "F", 
        "edad" : 34
    }, 
    {
        "id" : 8, 
        "nombre" : "Nariko", 
        "apellido" : "Le Bosse", 
        "email" : "nlebosse7@printfriendly.com", 
        "genero" : "F", 
        "edad" : 35
    }, 
    {
        "id" : 9, 
        "nombre" : "Aveline", 
        "apellido" : "Dumphry", 
        "email" : "adumphry8@pinterest.com", 
        "genero" : "F", 
        "edad" : 35
    }, 
    {
        "id" : 10, 
        "nombre" : "Jared", 
        "apellido" : "Swiffin", 
        "email" : "jswiffin9@virginia.edu", 
        "genero" : "M", 
        "edad" : 53
    }, 
    {
        "id" : 11, 
        "nombre" : "Gabrila", 
        "apellido" : "Korf", 
        "email" : "gkorfa@nytimes.com", 
        "genero" : "F", 
        "edad" : 30
    }, 
    {
        "id" : 12, 
        "nombre" : "Adan", 
        "apellido" : "Meenehan", 
        "email" : "ameenehanb@accuweather.com", 
        "genero" : "F", 
        "edad" : 35
    }, 
    {
        "id" : 13, 
        "nombre" : "Vilma", 
        "apellido" : "Anniwell", 
        "email" : "vanniwellc@flavors.me", 
        "genero" : "F", 
        "edad" : 54
    }, 
    {
        "id" : 14, 
        "nombre" : "Greg", 
        "apellido" : "Stoving", 
        "email" : "gstovingd@sfgate.com", 
        "genero" : "M", 
        "edad" : 22
    }, 
    {
        "id" : 15, 
        "nombre" : "Kirsti", 
        "apellido" : "Bartholomieu", 
        "email" : "kbartholomieue@ustream.tv", 
        "genero" : "F", 
        "edad" : 58
    }, 
    {
        "id" : 16, 
        "nombre" : "Helaine", 
        "apellido" : "Owain", 
        "email" : "howainf@businessinsider.com", 
        "genero" : "F", 
        "edad" : 52
    }, 
    {
        "id" : 17, 
        "nombre" : "Odie", 
        "apellido" : "Lamblin", 
        "email" : "olambling@cloudflare.com", 
        "genero" : "M", 
        "edad" : 75
    }, 
    {
        "id" : 18, 
        "nombre" : "Woody", 
        "apellido" : "Oakly", 
        "email" : "woaklyh@biglobe.ne.jp", 
        "genero" : "M", 
        "edad" : 18
    }, 
    {
        "id" : 19, 
        "nombre" : "Price", 
        "apellido" : "Orritt", 
        "email" : "porritti@fotki.com", 
        "genero" : "M", 
        "edad" : 57
    }, 
    {
        "id" : 20, 
        "nombre" : "Sampson", 
        "apellido" : "Hawes", 
        "email" : "shawesj@abc.net.au", 
        "genero" : "M", 
        "edad" : 31
    }, 
    {
        "id" : 21, 
        "nombre" : "Alex", 
        "apellido" : "Cardero", 
        "email" : "acarderok@sciencedirect.com", 
        "genero" : "M", 
        "edad" : 38
    }, 
    {
        "id" : 22, 
        "nombre" : "Tod", 
        "apellido" : "Licciardiello", 
        "email" : "tlicciardiellol@latimes.com", 
        "genero" : "M", 
        "edad" : 62
    }, 
    {
        "id" : 23, 
        "nombre" : "Eamon", 
        "apellido" : "Winger", 
        "email" : "ewingerm@intel.com", 
        "genero" : "M", 
        "edad" : 48
    }, 
    {
        "id" : 24, 
        "nombre" : "Freemon", 
        "apellido" : "Nairne", 
        "email" : "fnairnen@vimeo.com", 
        "genero" : "M", 
        "edad" : 22
    }, 
    {
        "id" : 25, 
        "nombre" : "Paxton", 
        "apellido" : "Delafont", 
        "email" : "pdelafonto@who.int", 
        "genero" : "M", 
        "edad" : 66
    }, 
    {
        "id" : 26, 
        "nombre" : "Tierney", 
        "apellido" : "Meace", 
        "email" : "tmeacep@msu.edu", 
        "genero" : "F", 
        "edad" : 31
    }, 
    {
        "id" : 27, 
        "nombre" : "Dougie", 
        "apellido" : "Henderson", 
        "email" : "dhendersonq@mail.ru", 
        "genero" : "M", 
        "edad" : 48
    }, 
    {
        "id" : 28, 
        "nombre" : "Berti", 
        "apellido" : "Skepper", 
        "email" : "bskepperr@cnn.com", 
        "genero" : "F", 
        "edad" : 73
    }, 
    {
        "id" : 29, 
        "nombre" : "Moira", 
        "apellido" : "Skerm", 
        "email" : "mskerms@netscape.com", 
        "genero" : "F", 
        "edad" : 59
    }, 
    {
        "id" : 30, 
        "nombre" : "Daile", 
        "apellido" : "Asbrey", 
        "email" : "dasbreyt@wikipedia.org", 
        "genero" : "F", 
        "edad" : 36
    }, 
    {
        "id" : 31, 
        "nombre" : "Erinn", 
        "apellido" : "Addenbrooke", 
        "email" : "eaddenbrookeu@oaic.gov.au", 
        "genero" : "F", 
        "edad" : 65
    }, 
    {
        "id" : 32, 
        "nombre" : "Lissa", 
        "apellido" : "Covendon", 
        "email" : "lcovendonv@surveymonkey.com", 
        "genero" : "F", 
        "edad" : 33
    }, 
    {
        "id" : 33, 
        "nombre" : "Reggie", 
        "apellido" : "Coghill", 
        "email" : "rcoghillw@cdc.gov", 
        "genero" : "M", 
        "edad" : 40
    }, 
    {
        "id" : 34, 
        "nombre" : "Nicky", 
        "apellido" : "Hanham", 
        "email" : "nhanhamx@spotify.com", 
        "genero" : "M", 
        "edad" : 18
    }, 
    {
        "id" : 35, 
        "nombre" : "Leigha", 
        "apellido" : "Fann", 
        "email" : "lfanny@paypal.com", 
        "genero" : "F", 
        "edad" : 74
    }, 
    {
        "id" : 36, 
        "nombre" : "Wally", 
        "apellido" : "McCathay", 
        "email" : "wmccathayz@vistaprint.com", 
        "genero" : "F", 
        "edad" : 51
    }, 
    {
        "id" : 37, 
        "nombre" : "Son", 
        "apellido" : "Larraway", 
        "email" : "slarraway10@uiuc.edu", 
        "genero" : "M", 
        "edad" : 79
    }, 
    {
        "id" : 38, 
        "nombre" : "Shane", 
        "apellido" : "Vannucci", 
        "email" : "svannucci11@altervista.org", 
        "genero" : "F", 
        "edad" : 18
    }, 
    {
        "id" : 39, 
        "nombre" : "Franklyn", 
        "apellido" : "Ride", 
        "email" : "fride12@spiegel.de", 
        "genero" : "M", 
        "edad" : 78
    }, 
    {
        "id" : 40, 
        "nombre" : "Em", 
        "apellido" : "Maunton", 
        "email" : "emaunton13@ibm.com", 
        "genero" : "M", 
        "edad" : 29
    }, 
    {
        "id" : 41, 
        "nombre" : "Emili", 
        "apellido" : "Rains", 
        "email" : "erains14@1688.com", 
        "genero" : "F", 
        "edad" : 70
    }, 
    {
        "id" : 42, 
        "nombre" : "Essy", 
        "apellido" : "Hanmore", 
        "email" : "ehanmore15@macromedia.com", 
        "genero" : "F", 
        "edad" : 29
    }, 
    {
        "id" : 43, 
        "nombre" : "Laurene", 
        "apellido" : "Bresnen", 
        "email" : "lbresnen16@mlb.com", 
        "genero" : "F", 
        "edad" : 43
    }, 
    {
        "id" : 44, 
        "nombre" : "Mallissa", 
        "apellido" : "Penson", 
        "email" : "mpenson17@behance.net", 
        "genero" : "F", 
        "edad" : 24
    }, 
    {
        "id" : 45, 
        "nombre" : "El", 
        "apellido" : "Boxill", 
        "email" : "eboxill18@shareasale.com", 
        "genero" : "M", 
        "edad" : 52
    }, 
    {
        "id" : 46, 
        "nombre" : "Maryellen", 
        "apellido" : "Squire", 
        "email" : "msquire19@gmpg.org", 
        "genero" : "F", 
        "edad" : 57
    }, 
    {
        "id" : 47, 
        "nombre" : "Melina", 
        "apellido" : "Blackwell", 
        "email" : "mblackwell1a@amazon.de", 
        "genero" : "F", 
        "edad" : 18
    }, 
    {
        "id" : 48, 
        "nombre" : "Jeannie", 
        "apellido" : "Dosedale", 
        "email" : "jdosedale1b@blogtalkradio.com", 
        "genero" : "F", 
        "edad" : 30
    }, 
    {
        "id" : 49, 
        "nombre" : "Walton", 
        "apellido" : "Croxon", 
        "email" : "wcroxon1c@amazon.com", 
        "genero" : "M", 
        "edad" : 58
    }, 
    {
        "id" : 50, 
        "nombre" : "Gretal", 
        "apellido" : "Shearman", 
        "email" : "gshearman1d@paginegialle.it", 
        "genero" : "F", 
        "edad" : 44
    }
]
